carrier_services/__init__.py
carrier_services/__main__.py
carrier_services/iaau.py
carrier_services/resources/code_table_unlocode_iaau.csv
carrier_services/utils/__init__.py
carrier_services/utils/config.dev.toml
carrier_services/utils/config.toml
carrier_services/utils/utils.py
carrier_services-0.3.0.dist-info/WHEEL
carrier_services-0.3.0.dist-info/METADATA
carrier_services-0.3.0.dist-info/RECORD
